openapi_agent/__init__.py
openapi_agent/agent.py
openapi_agent/agent_cache.py
openapi_agent/code_generator.py
openapi_agent/logging_config.py
openapi_agent/sandbox.py
openapi_agent/utils/__init__.py
openapi_agent/utils/logging_config.py
openapi_agent/utils/url_resolver.py
openapi_agent-0.1.3.dist-info/METADATA
openapi_agent-0.1.3.dist-info/WHEEL
openapi_agent-0.1.3.dist-info/RECORD
