Metadata-Version: 2.1
Name: openapi-agent
Version: 0.1.3
Summary: An OpenAPI agent that can execute operations based on natural language descriptions
Author: Jordi Montes Sanabria
Author-email: jordi@fewsats.com
Requires-Python: >=3.8,<4.0
Classifier: Programming Language :: Python :: 3
Classifier: Programming Language :: Python :: 3.8
Classifier: Programming Language :: Python :: 3.9
Classifier: Programming Language :: Python :: 3.10
Classifier: Programming Language :: Python :: 3.11
Classifier: Programming Language :: Python :: 3.12
Requires-Dist: cachetools
Requires-Dist: docker
Requires-Dist: fastapi
Requires-Dist: jsonref
Requires-Dist: langsmith
Requires-Dist: openai
Requires-Dist: openapi-spec-validator
Requires-Dist: pydantic
Requires-Dist: python-dotenv
Requires-Dist: pyyaml
Requires-Dist: uvicorn
